katonic/__init__.py
katonic/py.typed
katonic/version.py
katonic/genai/__init__.py
katonic/genai/core.py
katonic/llm/__init__.py
katonic/llm/__version__.py
katonic/llm/completion.py
katonic/llm/log_requests.py
katonic/llm/logutils.py
katonic/llm/platform_logger.py
katonic/llm/schemas.py
katonic/llm/encoders/Xenova_llama_3_tokenizer.pkl
katonic/llm/encoders/cl100k_base.pkl
katonic/llm/encoders/cohere_command_nightly.pkl
katonic/llm/encoders/hf_internal_testing_llama_tokenizer.pkl
katonic/llm/encoders/o200k_base.pkl
katonic/llm/models/__init__.py
katonic/llm/models/ai21_llm.py
katonic/llm/models/alephalpha_llm.py
katonic/llm/models/anthropic_llm.py
katonic/llm/models/anyscale_llm.py
katonic/llm/models/azure_llm.py
katonic/llm/models/bedrock_llm.py
katonic/llm/models/cohere_llm.py
katonic/llm/models/completion.py
katonic/llm/models/factory.py
katonic/llm/models/google_llm.py
katonic/llm/models/groq_llm.py
katonic/llm/models/huggingface_llm.py
katonic/llm/models/katonic_llm.py
katonic/llm/models/lighton_llm.py
katonic/llm/models/mappings.py
katonic/llm/models/nvidia_llm.py
katonic/llm/models/openai_chat_llm.py
katonic/llm/models/openai_llm.py
katonic/llm/models/openrouter_llm.py
katonic/llm/models/perplexity_llm.py
katonic/llm/models/replicate_llm.py
katonic/llm/models/sambanova_llm.py
katonic/llm/models/tgi_llm.py
katonic/llm/models/togetherai_llm.py
katonic/llm/models/vllm_llm.py
katonic/llm/multimodal/openai_vision.py
katonic/llm/platform_log/utilities/callback.py
katonic/llm/platform_log/utilities/config.py
katonic/llm/platform_log/utilities/constants.py
katonic/llm/platform_log/utilities/cost_handler.py
katonic/llm/platform_log/utilities/logutils.py
katonic/llm/platform_log/utilities/mongo_apis.py
katonic/llm/platform_log/utilities/mongo_init.py
katonic/llm/platform_log/utilities/prompts.py
katonic/llm/platform_log/utilities/schemas.py
katonic/llm/platform_log/utilities/token_verify.py
katonic/llm/platform_log/utilities/utils.py
katonic/llm/utilities/__init__.py
katonic_sdk-6.0.0.29rc0.dist-info/licenses/LICENSE
katonic_sdk-6.0.0.29rc0.dist-info/METADATA
katonic_sdk-6.0.0.29rc0.dist-info/WHEEL
katonic_sdk-6.0.0.29rc0.dist-info/top_level.txt
katonic_sdk-6.0.0.29rc0.dist-info/RECORD
