Metadata-Version: 2.4
Name: katonic-sdk
Version: 6.0.0.29rc0
Summary: A modern, enterprise-ready MLOps Python SDK
Author-email: "Katonic Pty Ltd." <shailesh.kumar@katonic.ai>
License: MIT
Project-URL: Homepage, https://www.katonic.ai/
Project-URL: Documentation, https://docs.katonic.ai/
Classifier: Programming Language :: Python :: 3.8
Classifier: Programming Language :: Python :: 3.9
Classifier: Programming Language :: Python :: 3.10
Classifier: Programming Language :: Python :: 3.11
Classifier: Programming Language :: Python :: 3.12
Requires-Python: >=3.8
License-File: LICENSE
Requires-Dist: boto3<2.0.0,>=1.19.12
Requires-Dist: LunarCalendar>=0.0.9
Requires-Dist: certifi>=2017.4.17
Requires-Dist: click<9.0.0,>=7.1.1
Requires-Dist: colorama>=0.4.0
Requires-Dist: convertdate>=2.1.2
Requires-Dist: cron-descriptor>=1.2.0
Requires-Dist: deprecation<3.0.0,>=2.1.0
Requires-Dist: func-timeout>=4.0.0
Requires-Dist: gunicorn<22.0.0,>=20.1.0
Requires-Dist: humanize>=3.0.0
Requires-Dist: importlib-metadata>=4.8.1; python_version < "3.10"
Requires-Dist: isodate>=0.6.0
Requires-Dist: markdown<4.0.0,>=3.0
Requires-Dist: mlflow<3.0.0,>=2.0.1
Requires-Dist: msgpack<2.0.0,>=1.0.0
Requires-Dist: packaging<25.0.0,>=21.2
Requires-Dist: parsedatetime>=2.0.0
Requires-Dist: protobuf<5.0.0,>=3.19.4
Requires-Dist: pyarrow<15.0.0,>=6.0.0
Requires-Dist: pydantic<3.0.0,>=1.8.2
Requires-Dist: pyparsing>=2.0.0
Requires-Dist: python-dateutil>=2.8.0
Requires-Dist: python-dotenv>=0.19.0
Requires-Dist: python-geohash>=0.8.0
Requires-Dist: pyyaml<7.0.0,>=5.3
Requires-Dist: requests<3.0.0,>=2.25.0
Requires-Dist: scikit-learn<2.0.0,>=1.1.3
Requires-Dist: tqdm<5.0.0,>=4.36.1
Requires-Dist: typing-extensions<5.0.0,>=3.10.0
Requires-Dist: zipp<4.0.0,>=3.5.0
Requires-Dist: fastapi<1.0.0,>=0.95.0
Requires-Dist: langchain<1.0.0,>=0.1.0
Requires-Dist: langchain-openai<1.0.0,>=0.0.5
Requires-Dist: langchain-anthropic<1.0.0,>=0.1.0
Requires-Dist: langchain-google-genai<3.0.0,>=1.0.0
Requires-Dist: langchain-groq<1.0.0,>=0.1.0
Requires-Dist: langchain-together<1.0.0,>=0.1.0
Requires-Dist: langchain-nvidia-ai-endpoints<1.0.0,>=0.1.0
Requires-Dist: langchain-community<1.0.0,>=0.0.10
Requires-Dist: cohere<6.0.0,>=4.0.0
Requires-Dist: replicate<2.0.0,>=0.8.0
Requires-Dist: aleph-alpha-client<4.0.0,>=2.0.0
Requires-Dist: google-api-python-client<3.0.0,>=2.0.0
Requires-Dist: huggingface-hub<1.0.0,>=0.15.0
Requires-Dist: transformers<5.0.0,>=4.20.0
Requires-Dist: tokenizers<1.0.0,>=0.13.0
Requires-Dist: tiktoken<1.0.0,>=0.3.0
Requires-Dist: pymongo<5.0.0,>=4.0.0
Requires-Dist: python-jose[cryptography]<4.0.0,>=3.3.0
Requires-Dist: cryptography<43.0.0,>=3.4.0
Requires-Dist: redis<7.0.0,>=4.0.0
Requires-Dist: loguru<1.0.0,>=0.6.0
Requires-Dist: openai<2.0.0,>=1.0.0
Requires-Dist: pycryptodome<4.0.0,>=3.10.0
Provides-Extra: dev
Requires-Dist: pytest>=6.0; extra == "dev"
Requires-Dist: pytest-cov; extra == "dev"
Requires-Dist: mypy; extra == "dev"
Requires-Dist: black; extra == "dev"
Requires-Dist: flake8; extra == "dev"
Dynamic: license-file
